hydradxapi/__init__.py
hydradxapi/__main__.py
hydradxapi/api.py
hydradxapi/base.py
hydradxapi/client.py
hydradxapi/pallets/__init__.py
hydradxapi/pallets/balances.py
hydradxapi/pallets/democracy.py
hydradxapi/pallets/fees.py
hydradxapi/pallets/omnipool.py
hydradxapi/pallets/oracle.py
hydradxapi/pallets/registry.py
hydradxapi/pallets/stableswap.py
hydradxapi/pallets/staking.py
hydradxapi/pallets/tokens.py
hydradxapi/pallets/uniques.py
hydradx_api-0.3.3.dist-info/LICENSE
hydradx_api-0.3.3.dist-info/WHEEL
hydradx_api-0.3.3.dist-info/METADATA
hydradx_api-0.3.3.dist-info/RECORD
