Metadata-Version: 2.1
Name: hydradx-api
Version: 0.3.3
Summary: HydraDX interface
Home-page: https://github.com/enthusiastmartin/hydradx-api
License: MIT OR Apache-2.0
Author: Martin Hloska
Author-email: martin.hloska@gmail.com
Requires-Python: >=3.9,<4.0
Classifier: License :: Other/Proprietary License
Classifier: Programming Language :: Python :: 3
Classifier: Programming Language :: Python :: 3.10
Classifier: Programming Language :: Python :: 3.9
Requires-Dist: click (>=8.1.7,<9.0.0)
Requires-Dist: pytest (>=7.4.2,<8.0.0)
Requires-Dist: substrate-interface (>=1.7.4,<2.0.0)
Project-URL: Repository, https://github.com/enthusiastmartin/hydradx-api
